[
	{
		"Rang": 1,
		"Nom du joueur": "Darkblue",
		"Temps": "02 min 45.230",
		"Temps intermédiaire1 (s)": "28.76",
		"Temps intermédiaire2 (s)": "108.8",
		"Temps intermédiaire3 (s)": "144.33",
		"Temps intermédiaire4 (s)": "198.15",
		"Temps intermédiaire5 (s)": "223.06",
		"Bonus temps (s)": "88"
	},
	{
		"Rang": 2,
		"Nom du joueur": "Fresco 1-4 | Darkblue",
		"Temps": "03 min 10.370",
		"Temps intermédiaire1 (s)": "28.5",
		"Temps intermédiaire2 (s)": "107.76",
		"Temps intermédiaire3 (s)": "144.82",
		"Temps intermédiaire4 (s)": "197.67",
		"Temps intermédiaire5 (s)": "223.26",
		"Bonus temps (s)": "65"
	},
	{
		"Rang": 3,
		"Nom du joueur": "CoubyStark",
		"Temps": "03 min 14.320",
		"Temps intermédiaire1 (s)": "28.36",
		"Temps intermédiaire2 (s)": "106.94",
		"Temps intermédiaire3 (s)": "144.21",
		"Temps intermédiaire4 (s)": "193.9",
		"Temps intermédiaire5 (s)": "219.25",
		"Bonus temps (s)": "52"
	},
	{
		"Rang": 4,
		"Nom du joueur": "VALTA",
		"Temps": "03 min 24.950",
		"Temps intermédiaire1 (s)": "28.82",
		"Temps intermédiaire2 (s)": "102.6",
		"Temps intermédiaire3 (s)": "141.32",
		"Temps intermédiaire4 (s)": "195.87",
		"Temps intermédiaire5 (s)": "220.46",
		"Bonus temps (s)": "49"
	}
]
